ceres/__init__.py
ceres/constants/__init__.py
ceres/constants/constants.py
ceres/models/__init__.py
ceres/models/gravity/__init__.py
ceres/models/gravity/gravityfield.py
ceres/models/gravity/pointmass.py
ceres/objects/__init__.py
ceres/objects/celestialbody.py
ceres/objects/spacecraft.py
ceres_nav-0.0.1a2.dist-info/LICENSE
ceres_nav-0.0.1a2.dist-info/METADATA
ceres_nav-0.0.1a2.dist-info/WHEEL
ceres_nav-0.0.1a2.dist-info/top_level.txt
ceres_nav-0.0.1a2.dist-info/RECORD
