Metadata-Version: 2.1
Name: ceres-nav
Version: 0.0.1a2
Summary: Celestial Estimation for Research, Exploration, and Science
Home-page: https://ceresnavigation.org/
Author: Chris Gnam
Author-email: crgnam@buffalo.edu
License: MIT
Download-URL: https://pypi.org/project/ceres-nav/
Project-URL: Source, https://github.com/ceres-navigation/ceres
Project-URL: Documentation, https://docs.ceresnavigation.org/
Project-URL: Bug Reports, https://github.com/ceres-navigation/ceres/issues
Platform: UNKNOWN
License-File: LICENSE
Requires-Dist: numpy
